salesfly/__init__.py
salesfly/errors.py
salesfly/geoip_api.py
salesfly/mail_api.py
salesfly/multipart.py
salesfly/pdf_api.py
salesfly/rest.py
salesfly/usage_api.py
salesfly/version.py
salesfly-1.0.0.dist-info/LICENSE
salesfly-1.0.0.dist-info/METADATA
salesfly-1.0.0.dist-info/WHEEL
salesfly-1.0.0.dist-info/top_level.txt
salesfly-1.0.0.dist-info/RECORD
